Metadata-Version: 1.1
Name: addon
Version: 0.0.2
Summary: Add all numbers
Home-page: UNKNOWN
Author: Jiganesh Patil
Author-email: jiganeshpatil01071999@gmail.com
License: MIT
Keywords: calculator
Platform: UNKNOWN
Classifier: Development Status :: 5 - Production/Stable
Classifier: Intended Audience :: Education
Classifier: Operating System :: Microsoft :: Windows :: Windows 10
Classifier: License :: OSI Approved :: MIT License
Classifier: Programming Language :: Python :: 3
